ibis_heavyai/__init__.py
ibis_heavyai/client.py
ibis_heavyai/compiler.py
ibis_heavyai/ddl.py
ibis_heavyai/dtypes.py
ibis_heavyai/geo.py
ibis_heavyai/identifiers.py
ibis_heavyai/operations.py
ibis_heavyai/udf.py
ibis_heavyai-1.1.dist-info/entry_points.txt
ibis_heavyai-1.1.dist-info/LICENSE.md
ibis_heavyai-1.1.dist-info/WHEEL
ibis_heavyai-1.1.dist-info/METADATA
ibis_heavyai-1.1.dist-info/RECORD
