Metadata-Version: 2.1
Name: ibis-heavyai
Version: 1.1
Summary: Ibis HeavyDB backend
Author-email: "Heavy.AI" <community@heavy.ai>
Requires-Python: >=3.7
Classifier: License :: OSI Approved :: Apache Software License
Classifier: Topic :: Database
Classifier: Topic :: Scientific/Engineering
Requires-Dist: ibis-framework >=2.0
Requires-Dist: heavyai
Requires-Dist: rbc-project >=0.8.0
Requires-Dist: pyarrow >=3.0.0
Requires-Dist: regex
Requires-Dist: pandas
Requires-Dist: shapely
Requires-Dist: geopandas
Requires-Dist: importlib_metadata
Requires-Dist: packaging
Requires-Dist: ibis-heavyai[test] ; extra == "dev"
Requires-Dist: pre-commit ; extra == "dev"
Requires-Dist: flit ; extra == "dev"
Requires-Dist: pytest ; extra == "test"
Requires-Dist: pytest-cov ; extra == "test"
Requires-Dist: pytest-mock ; extra == "test"
Requires-Dist: mock ; extra == "test"
Project-URL: Home, https://github.com/heavyai/ibis-heavyai
Project-URL: Source, https://github.com/heavyai/ibis-heavyai
Provides-Extra: dev
Provides-Extra: test
